cdhmm/__init__.py
cdhmm/cdhmm.py
cdhmm_ashishmokalkar-0.0.2.dist-info/LICENSE
cdhmm_ashishmokalkar-0.0.2.dist-info/METADATA
cdhmm_ashishmokalkar-0.0.2.dist-info/WHEEL
cdhmm_ashishmokalkar-0.0.2.dist-info/top_level.txt
cdhmm_ashishmokalkar-0.0.2.dist-info/RECORD
