Metadata-Version: 2.1
Name: cdhmm-ashishmokalkar
Version: 0.0.2
Summary: Python Library for Continuous Desity Hidden Markov Model which is widely used in Speech Recognition.
Home-page: https://github.com/ashishmokalkar/cdhmm
Author: Ashish Mokalkar
Author-email: ashishmokalkar79@gmail.com
License: UNKNOWN
Platform: UNKNOWN
Classifier: Programming Language :: Python :: 2
Classifier: License :: OSI Approved :: MIT License
Classifier: Operating System :: OS Independent
Requires-Python: >=2.7
